{
  "dialogue_id": "trainline34",
  "annotation_metadata": {
    "corpus": "SPAADIA",
    "version": "2.0",
    "date_annotated": "2023-10-15",
    "annotators": ["Annotator1", "Annotator2"],
    "inter_annotator_reliability": {
      "overall": 0.89,
      "frame_activation": 0.91,
      "strategy_selection": 0.87,
      "negotiation_points": 0.86
    }
  },
  "dialogue_statistics": {
    "turn_count": 59,
    "utterance_count": 164,
    "duration_seconds": 386,
    "word_count": 1845,
    "speaker_distribution": {
      "service_provider": 30,
      "customer": 29
    },
    "frame_statistics": {
      "frame_type_count": 17,
      "frame_transition_count": 36,
      "mean_activation_strength": 4.6,
      "dominant_frames": ["journey_information", "constraint_condition", "price_verification", "understanding_reception"]
    },
    "strategy_statistics": {
      "strategy_type_count": 26,
      "frame_reinforcement_percentage": 62.5,
      "frame_shifting_percentage": 30.8,
      "frame_blending_percentage": 4.3,
      "frame_acceptance_percentage": 2.4,
      "mean_strategy_efficacy": 4.3
    }
  },
  "coding_scheme": {
    "frame_types": {
      "service_initiation": "Initial service frame for opening a dialogue",
      "journey_information": "Frame for collecting journey details",
      "payment_method": "Frame related to payment options and methods",
      "preference_expression": "Frame for expressing customer preferences",
      "service_processing": "Frame related to operational processing",
      "discount_eligibility": "Frame for determining discount qualifications",
      "previous_experience": "Frame referencing customer's prior experiences",
      "clarification_request": "Frame for requesting additional information",
      "understanding_signaling": "Frame for indicating comprehension",
      "travel_options": "Frame presenting travel possibilities",
      "information_reception": "Frame signaling reception of information",
      "information_verification": "Frame for verifying correctness",
      "experiential_comparison": "Frame comparing with past experiences",
      "reasoning_inquiry": "Frame questioning rationales or explanations",
      "reasoning_explanation": "Frame providing rationales or explanations",
      "alternative_options": "Frame presenting alternative choices",
      "understanding_reception": "Frame signaling reception of information",
      "concern_expression": "Frame expressing worries or concerns",
      "contingency_planning": "Frame for exploring fallback options",
      "constraint_condition": "Frame outlining limitations or conditions",
      "alternative_seeking": "Frame searching for alternatives",
      "clarification_seeking": "Frame seeking clearer information",
      "solution_seeking": "Frame exploring potential solutions",
      "response_formulation": "Frame constructing a response",
      "journey_intention": "Frame expressing travel intentions",
      "alternative_consideration": "Frame considering different options",
      "price_verification": "Frame verifying price information",
      "price_information": "Frame providing price details",
      "conditional_pricing": "Frame explaining price conditions",
      "correction": "Frame correcting misunderstandings",
      "condition_verification": "Frame verifying conditions",
      "term_verification": "Frame confirming terminology",
      "option_presentation": "Frame presenting available options",
      "feature_verification": "Frame verifying service features",
      "feature_confirmation": "Frame confirming service features",
      "terminology_inquiry": "Frame inquiring about terminology",
      "terminology_provision": "Frame providing terminology information",
      "terminology_reception": "Frame receiving terminology information",
      "comparison_inquiry": "Frame inquiring about comparisons",
      "constraint_inquiry": "Frame inquiring about constraints",
      "decision_making": "Frame for making decisions",
      "interaction_closure": "Frame for closing the interaction",
      "conversation_termination": "Frame for terminating the conversation"
    },
    "strategy_types": {
      "frame_reinforcement": "Strategies that strengthen established frames",
      "frame_shifting": "Strategies that transition between frames",
      "frame_blending": "Strategies that integrate multiple frames",
      "frame_expansion": "Strategies that expand existing frames",
      "frame_acceptance": "Strategies that signal acceptance of frames"
    },
    "strategy_subtypes": {
      "initialization": "Establishing the initial conversational frame",
      "institution_identification": "Identifying the institutional context",
      "role_establishment": "Establishing interactional roles",
      "directive_guidance": "Providing guidance on next steps",
      "information_provision": "Supplying requested information",
      "topic_transition_marking": "Marking transitions between topics",
      "framework_expansion": "Expanding the conversational framework",
      "confirmation": "Confirming understanding or agreement",
      "reconfirmation": "Reinforcing previous confirmation",
      "information_elicitation": "Soliciting specific information",
      "self_correction": "Correcting one's own utterance",
      "additional_information": "Providing supplementary information",
      "detail_specification": "Offering specific details",
      "constraint_highlighting": "Emphasizing limitations",
      "procedural_requirement": "Stating necessary procedures",
      "acknowledgment": "Acknowledging receipt of information",
      "affirmation": "Expressing agreement",
      "preference_elicitation": "Seeking preference information",
      "preference_indication": "Indicating preferences",
      "cognitive_processing": "Signaling mental processing",
      "specific_preference": "Stating specific preferences",
      "preference_refinement": "Refining previously stated preferences",
      "task_commitment": "Expressing commitment to a task",
      "additional_requirement": "Stating additional needs",
      "negative_response": "Providing a negative answer",
      "response_reinforcement": "Reinforcing a previous response",
      "context_setting": "Establishing contextual background",
      "experience_reference": "Referencing past experiences",
      "prior_knowledge": "Indicating previous knowledge",
      "uncertainty_expression": "Expressing uncertainty",
      "procedural_explanation": "Explaining procedures",
      "clarification_request": "Requesting clarification",
      "understanding_signal": "Signaling comprehension",
      "information_reception": "Acknowledging information receipt",
      "requirement_specification": "Specifying requirements",
      "information_completion": "Completing information",
      "verification_request": "Requesting verification",
      "experience_comparison": "Comparing with past experiences",
      "alternative_reference": "Referencing alternatives",
      "assumption_expression": "Expressing assumptions",
      "explanation_offering": "Offering explanations",
      "explanation_request": "Requesting explanations",
      "explanation_provision": "Providing explanations",
      "alternative_suggestion": "Suggesting alternatives",
      "system_explanation": "Explaining system functionalities",
      "benefit_highlighting": "Emphasizing benefits",
      "realization_marker": "Marking realization moments",
      "concern_identification": "Identifying concerns",
      "assertion_strengthening": "Strengthening assertions",
      "context_provision": "Providing context",
      "contingency_seeking": "Seeking contingency options",
      "negative_preface": "Prefacing negative information",
      "condition_specification": "Specifying conditions",
      "constraint_identification": "Identifying constraints",
      "alternative_search": "Searching for alternatives",
      "transition_marking": "Marking transitions",
      "politeness_marker": "Marking politeness",
      "understanding_verification": "Verifying understanding",
      "clarification_provision": "Providing clarification",
      "constraint_expansion": "Expanding constraints",
      "surprise_marker": "Marking surprise",
      "alternative_exploration": "Exploring alternatives",
      "processing_marker": "Marking processing",
      "abandoned_utterance": "Abandoning an utterance",
      "intention_statement": "Stating intentions",
      "alternative_consideration": "Considering alternatives",
      "price_inquiry": "Inquiring about prices",
      "condition_introduction": "Introducing conditions",
      "price_specification": "Specifying prices",
      "conclusion_marking": "Marking conclusions",
      "correction_marker": "Marking corrections",
      "correction_provision": "Providing corrections",
      "condition_verification": "Verifying conditions",
      "term_repetition": "Repeating terminology",
      "condition_reiteration": "Reiterating conditions",
      "option_description": "Describing options",
      "feature_verification": "Verifying features",
      "flexibility_verification": "Verifying flexibility",
      "capability_confirmation": "Confirming capabilities",
      "abandoned_inquiry": "Abandoning an inquiry",
      "terminology_request": "Requesting terminology information",
      "terminology_provision": "Providing terminology information",
      "terminology_completion": "Completing terminology information",
      "hypothetical_scenario": "Presenting hypothetical scenarios",
      "price_repetition": "Repeating price information",
      "topic_shifting": "Shifting topics",
      "exception_acknowledgment": "Acknowledging exceptions",
      "negation_marker": "Marking negation",
      "negation_reinforcement": "Reinforcing negation",
      "feature_explanation": "Explaining features",
      "deliberation_marker": "Marking deliberation",
      "decision_postponement": "Postponing decisions",
      "need_expression": "Expressing needs",
      "future_action": "Indicating future actions",
      "appreciation_expression": "Expressing appreciation",
      "closure_acknowledgment": "Acknowledging closure",
      "formality_marker": "Marking formality",
      "conversation_closure": "Closing conversation",
      "appreciation_reciprocation": "Reciprocating appreciation",
      "rapport_building": "Building rapport"
    },
    "negotiation_types": {
      "opening": "Initial contact point in dialogue",
      "initiation": "Beginning of information exchange",
      "response": "Providing requested information",
      "transition": "Shifting between dialogue phases",
      "compliance": "Indicating agreement to proceed",
      "information": "Exchange of factual content",
      "preference": "Expression of personal choices",
      "constraint": "Introducing limitations",
      "acceptance": "Agreeing to constraints",
      "processing": "Indicating operational activities",
      "knowledge_display": "Demonstrating prior knowledge",
      "procedure": "Explaining process steps",
      "clarification": "Seeking or providing clearer information",
      "alignment": "Synchronizing understanding",
      "rapport": "Building interpersonal connection",
      "verification": "Checking correctness of information",
      "experience": "Referencing past experiences",
      "query": "Requesting specific information",
      "explanation": "Providing rationales",
      "option": "Presenting choices",
      "benefit": "Highlighting advantages",
      "realization": "Moment of understanding",
      "concern": "Expressing worries",
      "solution": "Seeking resolutions",
      "reception": "Acknowledging received information",
      "correction": "Fixing misunderstandings",
      "surprise": "Expressing unexpected realization",
      "intention": "Stating planned actions",
      "flexibility": "Indicating adaptability",
      "price": "Discussing financial aspects",
      "condition": "Specifying requirements",
      "repetition": "Repeating information",
      "feature": "Discussing service characteristics",
      "inquiry": "Seeking detailed information",
      "deliberation": "Considering options",
      "closure": "Ending interaction",
      "farewell": "Final leave-taking exchange"
    }
  },
  "research_links": {
    "hypotheses": ["H1", "H2", "H3", "H4"],
    "analytical_focus": {
      "H1": ["context_dependence", "institutional_presetting"],
      "H2": ["frame_type", "strategy_selection"],
      "H3": ["strategy_adaptation", "temporal_dynamics"],
      "H4": ["negotiation_points", "contribution_ratio"]
    }
  },
  "dialogue_summary": {
    "context": "Train ticket booking service call",
    "primary_goal": "Customer seeking to book a train journey from Edinburgh to Milton Keynes",
    "key_challenges": [
      "Super Advance tickets fully booked",
      "Customer comparing with previous journey experience",
      "Need to clarify pricing conditions"
    ],
    "resolution": "Customer postpones decision after receiving pricing information",
    "interaction_quality": {
      "communication_efficiency": 0.73,
      "problem_resolution_completeness": 0.68,
      "rapport_level": 0.71
    }
  },
  "comparative_metrics": {
    "frame_activation_intensity": {
      "trainline34": 4.6,
      "corpus_average": 4.3,
      "percentile": 76
    },
    "strategy_diversity": {
      "trainline34": 26,
      "corpus_average": 22,
      "percentile": 83
    },
    "negotiation_intensity": {
      "trainline34": 0.32,
      "corpus_average": 0.27,
      "percentile": 79
    }
  }
}